json2/__init__.py
json2-0.9.0.dist-info/LICENSE
json2-0.9.0.dist-info/METADATA
json2-0.9.0.dist-info/WHEEL
json2-0.9.0.dist-info/top_level.txt
json2-0.9.0.dist-info/RECORD
