Metadata-Version: 2.1
Name: json2
Version: 0.9.0
Summary: Add convenience function to pythons default json implementation
Home-page: https://github.com/ThoenigAdrian/json2
Author: Adrian Thoenig
Classifier: Programming Language :: Python :: 2
Classifier: Programming Language :: Python :: 3
Classifier: License :: OSI Approved :: MIT License
Classifier: Operating System :: OS Independent
Requires-Python: >=2.5
License-File: LICENSE
